banff/__init__.py
banff/_common/src/_log/__init__.py
banff/_common/src/_log/capture.py
banff/_common/src/_log/gensys_logger.py
banff/_common/src/_log/log_levels.py
banff/_common/src/diagnostics/__init__.py
banff/_common/src/diagnostics/gensys_diagnostics.py
banff/_common/src/diagnostics/memory_usage.py
banff/_common/src/diagnostics/time_measurement.py
banff/_common/src/exceptions/__init__.py
banff/_common/src/io_util/__init__.py
banff/_common/src/io_util/io_util.py
banff/_common/src/io_util/normalization.py
banff/_common/src/io_util/processing.py
banff/_common/src/io_util/type_converters.py
banff/_common/src/nls/__init__.py
banff/_common/src/nls/nls.py
banff/_common/src/nls/messages/en/LC_MESSAGES/gscommon.mo
banff/_common/src/nls/messages/fr/LC_MESSAGES/gscommon.mo
banff/_common/src/proc/__init__.py
banff/_common/src/proc/c_util.py
banff/_common/src/proc/error_handling.py
banff/_common/src/proc/loader.py
banff/_common/src/proc/stc_proc.py
banff/_common/src/proc/validation.py
banff/_common/src/testing/__init__.py
banff/_common/src/testing/assert_helper.py
banff/_common/src/testing/data_helper.py
banff/_common/src/testing/pytest_helper.py
banff/_log/__init__.py
banff/diagnostics/__init__.py
banff/exceptions/__init__.py
banff/io_util/__init__.py
banff/nls/__init__.py
banff/nls/nls.py
banff/nls/messages/en/LC_MESSAGES/banff.mo
banff/nls/messages/fr/LC_MESSAGES/banff.mo
banff/proc/__init__.py
banff/proc/banff_proc.py
banff/proc/proc_determin.py
banff/proc/proc_donorimp.py
banff/proc/proc_editstat.py
banff/proc/proc_errorloc.py
banff/proc/proc_estimato.py
banff/proc/proc_massimpu.py
banff/proc/proc_outlier.py
banff/proc/proc_prorate.py
banff/proc/proc_verifyed.py
banff/proc/bin/linux/x64/libdetermin_en.so
banff/proc/bin/linux/x64/libdetermin_fr.so
banff/proc/bin/linux/x64/libdonorimp_en.so
banff/proc/bin/linux/x64/libdonorimp_fr.so
banff/proc/bin/linux/x64/libeditstat_en.so
banff/proc/bin/linux/x64/libeditstat_fr.so
banff-3.1.3.dist-info/METADATA
banff-3.1.3.dist-info/WHEEL
banff-3.1.3.dist-info/top_level.txt
banff-3.1.3.dist-info/zip-safe
banff-3.1.3.dist-info/RECORD
banff-3.1.3.dist-info/licenses/LICENSE
