Metadata-Version: 2.4
Name: banff
Version: 3.1.3
Summary: Initial Banff package
Author-email: Stephen Arsenualt <stephen.arsenault@statcan.gc.ca>
Maintainer-email: "Banff Support, Statistics Canada" <statcan.banff-banff.statcan@statcan.gc.ca>
License:                     GNU GENERAL PUBLIC LICENSE
Project-URL: Homepage, https://github.com/StatCan/gensol-banff
Project-URL: Bug Tracker, https://github.com/StatCan/gensol-banff/issues
Classifier: Development Status :: 5 - Production/Stable
Classifier: Programming Language :: Python :: 3
Classifier: License :: OSI Approved :: GNU General Public License v3 or later (GPLv3+)
Requires-Python: >=3.10
License-File: LICENSE
Requires-Dist: pandas<3,>=2.0.0
Requires-Dist: pandas[parquet]>=2.0.0
Requires-Dist: pyarrow<19,>=14.0.0
Requires-Dist: nanoarrow<0.7,>=0.5.0
Requires-Dist: duckdb<2,>=0.7.0
Provides-Extra: test
Requires-Dist: pytest; extra == "test"
Requires-Dist: pytest-cov; extra == "test"
Provides-Extra: performance
Requires-Dist: pandas[performance]; extra == "performance"
Provides-Extra: diagnostics
Requires-Dist: psutil; extra == "diagnostics"
Provides-Extra: dev
Requires-Dist: banff[test]; extra == "dev"
Requires-Dist: ruff; extra == "dev"
Provides-Extra: doc
Requires-Dist: sphinx; extra == "doc"
Requires-Dist: sphinx_rtd_theme; extra == "doc"
Requires-Dist: pydata-sphinx-theme; extra == "doc"
Requires-Dist: myst_parser; extra == "doc"
Dynamic: license-file
